AUTHORS.rst
CONTRIBUTING.rst
HISTORY.rst
LICENSE
MANIFEST.in
README.rst
setup.cfg
setup.py
docs/Makefile
docs/authors.rst
docs/conf.py
docs/contributing.rst
docs/history.rst
docs/index.rst
docs/installation.rst
docs/make.bat
docs/readme.rst
docs/usage.rst
pydonitest/__init__.py
pydonitest/cli.py
pydonitest/db.py
pydonitest.egg-info/PKG-INFO
pydonitest.egg-info/SOURCES.txt
pydonitest.egg-info/dependency_links.txt
pydonitest.egg-info/entry_points.txt
pydonitest.egg-info/not-zip-safe
pydonitest.egg-info/requires.txt
pydonitest.egg-info/top_level.txt
tests/.DS_Store
tests/__init__.py
tests/test_pydonitest.py
tests/test_data/.DS_Store
tests/test_data/csv/mtcars.csv
tests/test_data/img/sample_image_to_ocr.png
tests/test_data/txt/.DS_Store
tests/test_data/txt/textfile.txt
tests/test_data/txt/textfile_empty.txt
tests/test_data/txt/nonempty_dir_flat/.DS_Store
tests/test_data/txt/nonempty_dir_flat/textfile_1.txt
tests/test_data/txt/nonempty_dir_flat/textfile_10.txt
tests/test_data/txt/nonempty_dir_flat/textfile_11.txt
tests/test_data/txt/nonempty_dir_flat/textfile_12.txt
tests/test_data/txt/nonempty_dir_flat/textfile_13.txt
tests/test_data/txt/nonempty_dir_flat/textfile_14.txt
tests/test_data/txt/nonempty_dir_flat/textfile_15.txt
tests/test_data/txt/nonempty_dir_flat/textfile_16.txt
tests/test_data/txt/nonempty_dir_flat/textfile_17.txt
tests/test_data/txt/nonempty_dir_flat/textfile_18.txt
tests/test_data/txt/nonempty_dir_flat/textfile_19.txt
tests/test_data/txt/nonempty_dir_flat/textfile_2.txt
tests/test_data/txt/nonempty_dir_flat/textfile_20.txt
tests/test_data/txt/nonempty_dir_flat/textfile_21.txt
tests/test_data/txt/nonempty_dir_flat/textfile_22.txt
tests/test_data/txt/nonempty_dir_flat/textfile_23.txt
tests/test_data/txt/nonempty_dir_flat/textfile_24.txt
tests/test_data/txt/nonempty_dir_flat/textfile_25.txt
tests/test_data/txt/nonempty_dir_flat/textfile_3.txt
tests/test_data/txt/nonempty_dir_flat/textfile_4.txt
tests/test_data/txt/nonempty_dir_flat/textfile_5.txt
tests/test_data/txt/nonempty_dir_flat/textfile_6.txt
tests/test_data/txt/nonempty_dir_flat/textfile_7.txt
tests/test_data/txt/nonempty_dir_flat/textfile_8.txt
tests/test_data/txt/nonempty_dir_flat/textfile_9.txt
