Metadata-Version: 1.2
Name: pydonitest
Version: 0.1.12
Summary: A Python module for custom-built tools and maintained by Andoni Sooklaris.
Home-page: https://github.com/tsouchlarakis/pydonitest
Author: Andoni Sooklaris
Author-email: andoni.sooklaris@gmail.com
License: MIT license
Keywords: pydonitest
Platform: UNKNOWN
Classifier: Development Status :: 2 - Pre-Alpha
Classifier: Intended Audience :: Developers
Classifier: License :: OSI Approved :: MIT License
Classifier: Natural Language :: English
Classifier: Programming Language :: Python :: 3
Classifier: Programming Language :: Python :: 3.6
Classifier: Programming Language :: Python :: 3.7
Classifier: Programming Language :: Python :: 3.8
Classifier: Programming Language :: Python :: 3.9
Requires-Python: >=3.6
